{"created_at":"Mon Oct 17 11:13:20 +0000 2011","id":125892140940267522,"id_str":"125892140940267522","text":"Cool @apple \/ Steve Jobs infographic http:\/\/t.co\/Prb5yx4X @MickH87 - timeline history","source":"web","truncated":false,"in_reply_to_status_id":null,"in_reply_to_status_id_str":null,"in_reply_to_user_id":null,"in_reply_to_user_id_str":null,"in_reply_to_screen_name":null,"user":{"id":57618569,"id_str":"57618569","name":"James ","screen_name":"_JimLeo","location":"Leeds","url":"http:\/\/travelourtrip.co.uk","description":"Aston Villa fan, lover of all things digital, Search Consultant @bloomagency, currently residing in Leeds. Wants to travel more.","protected":false,"followers_count":279,"friends_count":408,"listed_count":10,"created_at":"Fri Jul 17 11:26:38 +0000 2009","favourites_count":54,"utc_offset":0,"time_zone":"London","geo_enabled":false,"verified":false,"statuses_count":2891,"lang":"en","contributors_enabled":false,"is_translator":false,"profile_background_color":"131516","profile_background_image_url":"http:\/\/a0.twimg.com\/profile_background_images\/414920336\/banig1.jpg","profile_background_image_url_https":"https:\/\/si0.twimg.com\/profile_background_images\/414920336\/banig1.jpg","profile_background_tile":true,"profile_image_url":"http:\/\/a0.twimg.com\/profile_images\/1655548720\/New_Image_normal.JPG","profile_image_url_https":"https:\/\/si0.twimg.com\/profile_images\/1655548720\/New_Image_normal.JPG","profile_banner_url":"https:\/\/si0.twimg.com\/profile_banners\/57618569\/1355849949","profile_link_color":"009999","profile_sidebar_border_color":"EEEEEE","profile_sidebar_fill_color":"EFEFEF","profile_text_color":"333333","profile_use_background_image":true,"default_profile":false,"default_profile_image":false,"following":null,"follow_request_sent":null,"notifications":null},"geo":null,"coordinates":null,"place":null,"contributors":null,"retweet_count":0,"favorite_count":0,"favorited":false,"retweeted":false,"possibly_sensitive":false,"lang":"en"}