{"created_at":"Mon Oct 17 14:04:53 +0000 2011","id":125935314878476289,"id_str":"125935314878476289","text":"@apple @iphone sold more because its in more retail duhhhh. Also woz is correct people dont want tech answer just simple child like ones ok!","source":"web","truncated":false,"in_reply_to_status_id":null,"in_reply_to_status_id_str":null,"in_reply_to_user_id":380749300,"in_reply_to_user_id_str":"380749300","in_reply_to_screen_name":"Apple","user":{"id":380655265,"id_str":"380655265","name":"James Stein","screen_name":"techwatchtower","location":"","url":null,"description":"Hi,\r\n\r\ni feel like i need to be a 'techwatchtower', so from time to time i will make tech reviews, opinions, etc...\r\n\r\nbye\r\n\r\ntechwatchtower ","protected":false,"followers_count":3,"friends_count":21,"listed_count":0,"created_at":"Tue Sep 27 00:50:55 +0000 2011","favourites_count":0,"utc_offset":null,"time_zone":null,"geo_enabled":false,"verified":false,"statuses_count":18,"lang":"en","contributors_enabled":false,"is_translator":false,"profile_background_color":"505657","profile_background_image_url":"http:\/\/a0.twimg.com\/images\/themes\/theme1\/bg.png","profile_background_image_url_https":"https:\/\/si0.twimg.com\/images\/themes\/theme1\/bg.png","profile_background_tile":false,"profile_image_url":"http:\/\/a0.twimg.com\/profile_images\/1589805612\/stock-photo-circuit-board_normal.jpg","profile_image_url_https":"https:\/\/si0.twimg.com\/profile_images\/1589805612\/stock-photo-circuit-board_normal.jpg","profile_link_color":"FF3300","profile_sidebar_border_color":"5C8A8C","profile_sidebar_fill_color":"030303","profile_text_color":"F0E7F0","profile_use_background_image":true,"default_profile":false,"default_profile_image":false,"following":null,"follow_request_sent":null,"notifications":null},"geo":null,"coordinates":null,"place":null,"contributors":null,"retweet_count":0,"favorite_count":0,"favorited":false,"retweeted":false,"lang":"en"}