{"created_at":"Wed Oct 19 02:08:55 +0000 2011","id":126479912407273472,"id_str":"126479912407273472","text":"Jus updated my computer to Windows 7 .....I'm on thanks to #microsoft","source":"\u003ca href=\"http:\/\/levelupstudio.com\/plume\" rel=\"nofollow\"\u003ePlume\u00a0for\u00a0Android\u003c\/a\u003e","truncated":false,"in_reply_to_status_id":null,"in_reply_to_status_id_str":null,"in_reply_to_user_id":null,"in_reply_to_user_id_str":null,"in_reply_to_screen_name":null,"user":{"id":97564404,"id_str":"97564404","name":"Ms.Drea","screen_name":"drea_sara","location":"In A Successful World!","url":null,"description":"Ambitious, Educated, and Determined Future Attorney! \n\nImproving my Life day by day!\n","protected":false,"followers_count":347,"friends_count":316,"listed_count":5,"created_at":"Fri Dec 18 01:03:28 +0000 2009","favourites_count":1,"utc_offset":-25200,"time_zone":"Mountain Time (US & Canada)","geo_enabled":false,"verified":false,"statuses_count":5052,"lang":"en","contributors_enabled":false,"is_translator":false,"profile_background_color":"131516","profile_background_image_url":"http:\/\/a0.twimg.com\/profile_background_images\/168182099\/me_doing_my_thing_.jpg","profile_background_image_url_https":"https:\/\/si0.twimg.com\/profile_background_images\/168182099\/me_doing_my_thing_.jpg","profile_background_tile":true,"profile_image_url":"http:\/\/a0.twimg.com\/profile_images\/2216976040\/C360_2012-05-06-14-49-38_normal.jpg","profile_image_url_https":"https:\/\/si0.twimg.com\/profile_images\/2216976040\/C360_2012-05-06-14-49-38_normal.jpg","profile_link_color":"009999","profile_sidebar_border_color":"EEEEEE","profile_sidebar_fill_color":"EFEFEF","profile_text_color":"333333","profile_use_background_image":true,"default_profile":false,"default_profile_image":false,"following":null,"follow_request_sent":null,"notifications":null},"geo":null,"coordinates":null,"place":null,"contributors":null,"retweet_count":0,"favorite_count":0,"favorited":false,"retweeted":false,"lang":"en"}