{"created_at":"Wed Oct 19 02:50:04 +0000 2011","id":126490265463701504,"id_str":"126490265463701504","text":"#Google announces dates for 2012 IO http:\/\/t.co\/90xoKyQN","source":"\u003ca href=\"http:\/\/www.hootsuite.com\" rel=\"nofollow\"\u003eHootSuite\u003c\/a\u003e","truncated":false,"in_reply_to_status_id":null,"in_reply_to_status_id_str":null,"in_reply_to_user_id":null,"in_reply_to_user_id_str":null,"in_reply_to_screen_name":null,"user":{"id":23478246,"id_str":"23478246","name":"Startup Tech Guy","screen_name":"startuptechguy","location":"United States","url":"http:\/\/www.nibletz.com","description":"Founder http:\/\/nibletz.com the voice of startups everywhere else. Creatorhttp:\/\/everywhereelse.co. My rebel mouse: http:\/\/startuptechguy.com Live from #sxsw13","protected":false,"followers_count":97258,"friends_count":21957,"listed_count":3472,"created_at":"Mon Mar 09 18:43:21 +0000 2009","favourites_count":4,"utc_offset":-18000,"time_zone":"Eastern Time (US & Canada)","geo_enabled":true,"verified":false,"statuses_count":95781,"lang":"en","contributors_enabled":false,"is_translator":false,"profile_background_color":"131516","profile_background_image_url":"http:\/\/a0.twimg.com\/images\/themes\/theme14\/bg.gif","profile_background_image_url_https":"https:\/\/si0.twimg.com\/images\/themes\/theme14\/bg.gif","profile_background_tile":true,"profile_image_url":"http:\/\/a0.twimg.com\/profile_images\/3436481582\/4fcce93f3f2754b37b0b70d5e3196f91_normal.jpeg","profile_image_url_https":"https:\/\/si0.twimg.com\/profile_images\/3436481582\/4fcce93f3f2754b37b0b70d5e3196f91_normal.jpeg","profile_link_color":"009999","profile_sidebar_border_color":"EEEEEE","profile_sidebar_fill_color":"EFEFEF","profile_text_color":"333333","profile_use_background_image":true,"default_profile":false,"default_profile_image":false,"following":null,"follow_request_sent":null,"notifications":null},"geo":null,"coordinates":null,"place":null,"contributors":null,"retweet_count":3,"favorite_count":0,"favorited":false,"retweeted":false,"possibly_sensitive":false,"lang":"en"}