{"created_at":"Wed Oct 19 03:05:18 +0000 2011","id":126494100252925954,"id_str":"126494100252925954","text":"#ICS is Sick, good work #google team","source":"web","truncated":false,"in_reply_to_status_id":null,"in_reply_to_status_id_str":null,"in_reply_to_user_id":null,"in_reply_to_user_id_str":null,"in_reply_to_screen_name":null,"user":{"id":19489306,"id_str":"19489306","name":"Jose Roa","screen_name":"jroa82v","location":"Buffalo, Ny","url":null,"description":"Loco Con mis Servidores Unix y mi Paisito R.D...I Love the Gym and my Unix\/Linux Servers and recently with android !!!","protected":false,"followers_count":105,"friends_count":249,"listed_count":0,"created_at":"Sun Jan 25 14:20:16 +0000 2009","favourites_count":1,"utc_offset":-18000,"time_zone":"Eastern Time (US & Canada)","geo_enabled":false,"verified":false,"statuses_count":681,"lang":"en","contributors_enabled":false,"is_translator":false,"profile_background_color":"9AE4E8","profile_background_image_url":"http:\/\/a0.twimg.com\/profile_background_images\/4307072\/Fedora_Jail_Linux_Wallpapers_Tux_Or_TBag_Prison_Break.jpg","profile_background_image_url_https":"https:\/\/si0.twimg.com\/profile_background_images\/4307072\/Fedora_Jail_Linux_Wallpapers_Tux_Or_TBag_Prison_Break.jpg","profile_background_tile":false,"profile_image_url":"http:\/\/a0.twimg.com\/profile_images\/1573249243\/megym_normal.jpg","profile_image_url_https":"https:\/\/si0.twimg.com\/profile_images\/1573249243\/megym_normal.jpg","profile_link_color":"0084B4","profile_sidebar_border_color":"BDDCAD","profile_sidebar_fill_color":"DDFFCC","profile_text_color":"333333","profile_use_background_image":true,"default_profile":false,"default_profile_image":false,"following":null,"follow_request_sent":null,"notifications":null},"geo":null,"coordinates":null,"place":null,"contributors":null,"retweet_count":0,"favorite_count":0,"favorited":false,"retweeted":false,"lang":"en"}