{"created_at":"Wed Oct 19 08:35:10 +0000 2011","id":126577114005782528,"id_str":"126577114005782528","text":"#Free Genuine Copy #Microsoft #Windows 8 Pre-Beta #OS: I don\u2019t know how long it\u2019s been out\u2026 http:\/\/t.co\/EY8GOIrk","source":"\u003ca href=\"http:\/\/www.google.com\/\" rel=\"nofollow\"\u003eGoogle\u003c\/a\u003e","truncated":false,"in_reply_to_status_id":null,"in_reply_to_status_id_str":null,"in_reply_to_user_id":null,"in_reply_to_user_id_str":null,"in_reply_to_screen_name":null,"user":{"id":54322264,"id_str":"54322264","name":"den-i","screen_name":"denicocc","location":"","url":"http:\/\/den-i.net","description":"Blogger and amateur web graphics designer","protected":false,"followers_count":53,"friends_count":146,"listed_count":0,"created_at":"Mon Jul 06 20:28:20 +0000 2009","favourites_count":0,"utc_offset":28800,"time_zone":"Kuala Lumpur","geo_enabled":false,"verified":false,"statuses_count":308,"lang":"en","contributors_enabled":false,"is_translator":false,"profile_background_color":"C0DEED","profile_background_image_url":"http:\/\/a0.twimg.com\/images\/themes\/theme1\/bg.png","profile_background_image_url_https":"https:\/\/si0.twimg.com\/images\/themes\/theme1\/bg.png","profile_background_tile":false,"profile_image_url":"http:\/\/a0.twimg.com\/profile_images\/301914449\/den-300_normal.png","profile_image_url_https":"https:\/\/si0.twimg.com\/profile_images\/301914449\/den-300_normal.png","profile_link_color":"0084B4","profile_sidebar_border_color":"C0DEED","profile_sidebar_fill_color":"DDEEF6","profile_text_color":"333333","profile_use_background_image":true,"default_profile":true,"default_profile_image":false,"following":null,"follow_request_sent":null,"notifications":null},"geo":null,"coordinates":null,"place":null,"contributors":null,"retweet_count":0,"favorite_count":0,"favorited":false,"retweeted":false,"possibly_sensitive":false,"lang":"en"}