{"created_at":"Wed Oct 19 04:00:40 +0000 2011","id":126508035416928256,"id_str":"126508035416928256","text":"RT @BatzayaB: #Google #Android Ice Cream Sandwich 4.0 (photos) http:\/\/t.co\/XlJBYgIS","source":"\u003ca href=\"http:\/\/www.tweetdeck.com\" rel=\"nofollow\"\u003eTweetDeck\u003c\/a\u003e","truncated":false,"in_reply_to_status_id":null,"in_reply_to_status_id_str":null,"in_reply_to_user_id":null,"in_reply_to_user_id_str":null,"in_reply_to_screen_name":null,"user":{"id":17618205,"id_str":"17618205","name":"NMMA Team","screen_name":"NMMAteam","location":"Ulaanbaatar, Mongolia","url":"http:\/\/newmediamarketingagency.com\/","description":"The New Media Marketing Agency is a creative web design, mobile application development and social media marketing firm.","protected":false,"followers_count":5011,"friends_count":114,"listed_count":86,"created_at":"Tue Nov 25 12:25:49 +0000 2008","favourites_count":68,"utc_offset":28800,"time_zone":"Ulaan Bataar","geo_enabled":false,"verified":false,"statuses_count":4724,"lang":"en","contributors_enabled":false,"is_translator":false,"profile_background_color":"C0DEED","profile_background_image_url":"http:\/\/a0.twimg.com\/profile_background_images\/346516691\/Twitter.jpg","profile_background_image_url_https":"https:\/\/si0.twimg.com\/profile_background_images\/346516691\/Twitter.jpg","profile_background_tile":false,"profile_image_url":"http:\/\/a0.twimg.com\/profile_images\/2759297951\/17069d8e3fce6cb57ade52b036c91001_normal.png","profile_image_url_https":"https:\/\/si0.twimg.com\/profile_images\/2759297951\/17069d8e3fce6cb57ade52b036c91001_normal.png","profile_banner_url":"https:\/\/si0.twimg.com\/profile_banners\/17618205\/1351097595","profile_link_color":"0084B4","profile_sidebar_border_color":"FFFFFF","profile_sidebar_fill_color":"DDEEF6","profile_text_color":"333333","profile_use_background_image":true,"default_profile":false,"default_profile_image":false,"following":null,"follow_request_sent":null,"notifications":null},"geo":null,"coordinates":null,"place":null,"contributors":null,"retweet_count":0,"favorite_count":0,"favorited":false,"retweeted":false,"possibly_sensitive":false,"lang":"id"}