{"created_at":"Wed Oct 19 14:39:21 +0000 2011","id":126668764199665664,"id_str":"126668764199665664","text":"High Tech Director of Business Development *selling consulting services* #Oracle #Microsoft #SAP #SanFrancisco #jobs http:\/\/t.co\/OWf25yJB","source":"web","truncated":false,"in_reply_to_status_id":null,"in_reply_to_status_id_str":null,"in_reply_to_user_id":null,"in_reply_to_user_id_str":null,"in_reply_to_screen_name":null,"user":{"id":39723102,"id_str":"39723102","name":"Amber Shankland","screen_name":"aqualimeblue","location":"Oxfordshire","url":"http:\/\/www.aqua-lime.co.uk","description":"Singer, Tribal Belly Dancer & Teacher, Nia,  Energy Healer, Aqua Lime - Executive Head Hunter - Consulting, Sales, Technology, currently onsite at Wipro, Pagan","protected":false,"followers_count":5635,"friends_count":1754,"listed_count":13,"created_at":"Wed May 13 10:03:53 +0000 2009","favourites_count":74,"utc_offset":0,"time_zone":"London","geo_enabled":true,"verified":false,"statuses_count":3138,"lang":"en","contributors_enabled":false,"is_translator":false,"profile_background_color":"07090B","profile_background_image_url":"http:\/\/a0.twimg.com\/profile_background_images\/66391857\/x4c881e880a6b8b94759b6d6469bdc06.jpg","profile_background_image_url_https":"https:\/\/si0.twimg.com\/profile_background_images\/66391857\/x4c881e880a6b8b94759b6d6469bdc06.jpg","profile_background_tile":true,"profile_image_url":"http:\/\/a0.twimg.com\/profile_images\/2936941477\/7b8b9f8a20b80359cee094547fe4360d_normal.jpeg","profile_image_url_https":"https:\/\/si0.twimg.com\/profile_images\/2936941477\/7b8b9f8a20b80359cee094547fe4360d_normal.jpeg","profile_link_color":"C34242","profile_sidebar_border_color":"BFBFBF","profile_sidebar_fill_color":"C9C9C9","profile_text_color":"1C1F23","profile_use_background_image":true,"default_profile":false,"default_profile_image":false,"following":null,"follow_request_sent":null,"notifications":null},"geo":null,"coordinates":null,"place":null,"contributors":null,"retweet_count":0,"favorite_count":0,"favorited":false,"retweeted":false,"possibly_sensitive":false,"lang":"en"}