{"created_at":"Wed Oct 19 20:29:18 +0000 2011","id":126756834257285120,"id_str":"126756834257285120","text":"#seguridadparatodos is using #Microsoft #Security #Essentials and you? (thx @msftsecresponse) - Our analysis [Spanish] http:\/\/t.co\/hUt3FQyA","source":"web","truncated":false,"in_reply_to_status_id":null,"in_reply_to_status_id_str":null,"in_reply_to_user_id":null,"in_reply_to_user_id_str":null,"in_reply_to_screen_name":null,"user":{"id":364286809,"id_str":"364286809","name":"Seguridad para Todos","screen_name":"seguridadxato2","location":"C\u00f3rdoba - Andalucia (Spain)","url":"http:\/\/www.seguridadparatodos.es","description":"Blog en Espa\u00f1ol especializado en Seguridad de la Informaci\u00f3n.\r\n(#Hacking, #Pentesting, #Compliance, #Auditorias, #Consultor\u00eda) ","protected":false,"followers_count":827,"friends_count":89,"listed_count":35,"created_at":"Mon Aug 29 14:34:16 +0000 2011","favourites_count":168,"utc_offset":3600,"time_zone":"Madrid","geo_enabled":false,"verified":false,"statuses_count":2539,"lang":"es","contributors_enabled":false,"is_translator":false,"profile_background_color":"E3DEDB","profile_background_image_url":"http:\/\/a0.twimg.com\/profile_background_images\/839213155\/b2539aef01d5a7dd1a9779e084fcd587.png","profile_background_image_url_https":"https:\/\/si0.twimg.com\/profile_background_images\/839213155\/b2539aef01d5a7dd1a9779e084fcd587.png","profile_background_tile":false,"profile_image_url":"http:\/\/a0.twimg.com\/profile_images\/3502363781\/de94100047d4c341e25eb1c5db68ea79_normal.png","profile_image_url_https":"https:\/\/si0.twimg.com\/profile_images\/3502363781\/de94100047d4c341e25eb1c5db68ea79_normal.png","profile_link_color":"2FC2EF","profile_sidebar_border_color":"FFFFFF","profile_sidebar_fill_color":"EBEBEB","profile_text_color":"666666","profile_use_background_image":true,"default_profile":false,"default_profile_image":false,"following":null,"follow_request_sent":null,"notifications":null},"geo":null,"coordinates":null,"place":null,"contributors":null,"retweet_count":0,"favorite_count":0,"favorited":false,"retweeted":false,"possibly_sensitive":false,"lang":"en"}