{"created_at":"Wed Oct 19 18:11:54 +0000 2011","id":126722253579763712,"id_str":"126722253579763712","text":"Project Greenwich 2 be released by #Microsoft Research lets people curate their own personal history http:\/\/t.co\/ocre5FwU","source":"web","truncated":false,"in_reply_to_status_id":null,"in_reply_to_status_id_str":null,"in_reply_to_user_id":null,"in_reply_to_user_id_str":null,"in_reply_to_screen_name":null,"user":{"id":51758198,"id_str":"51758198","name":"Babu Subramanian","screen_name":"babusubramanian","location":"Bangalore","url":null,"description":"Technology buff\r\nFilm buff","protected":false,"followers_count":591,"friends_count":1196,"listed_count":6,"created_at":"Sun Jun 28 15:41:08 +0000 2009","favourites_count":0,"utc_offset":19800,"time_zone":"New Delhi","geo_enabled":false,"verified":false,"statuses_count":2881,"lang":"en","contributors_enabled":false,"is_translator":false,"profile_background_color":"C0DEED","profile_background_image_url":"http:\/\/a0.twimg.com\/profile_background_images\/137703519\/DSCN0779.JPG","profile_background_image_url_https":"https:\/\/si0.twimg.com\/profile_background_images\/137703519\/DSCN0779.JPG","profile_background_tile":true,"profile_image_url":"http:\/\/a0.twimg.com\/profile_images\/1106904399\/DSCN0745_normal.JPG","profile_image_url_https":"https:\/\/si0.twimg.com\/profile_images\/1106904399\/DSCN0745_normal.JPG","profile_link_color":"0084B4","profile_sidebar_border_color":"C0DEED","profile_sidebar_fill_color":"DDEEF6","profile_text_color":"333333","profile_use_background_image":true,"default_profile":false,"default_profile_image":false,"following":null,"follow_request_sent":null,"notifications":null},"geo":null,"coordinates":null,"place":null,"contributors":null,"retweet_count":0,"favorite_count":0,"favorited":false,"retweeted":false,"possibly_sensitive":false,"lang":"en"}