{"created_at":"Wed Oct 19 19:57:15 +0000 2011","id":126748764869378048,"id_str":"126748764869378048","text":"RT @aislyngreene: #Microsoft wants to transform your hand into a touchscreen: http:\/\/t.co\/an3bmArc via @AddThis","source":"\u003ca href=\"http:\/\/www.tweetdeck.com\" rel=\"nofollow\"\u003eTweetDeck\u003c\/a\u003e","truncated":false,"in_reply_to_status_id":null,"in_reply_to_status_id_str":null,"in_reply_to_user_id":null,"in_reply_to_user_id_str":null,"in_reply_to_screen_name":null,"user":{"id":16407254,"id_str":"16407254","name":"George Erb","screen_name":"PSBJEditor","location":"Seattle","url":null,"description":"George Erb is editor of the Seattle-based Puget Sound Business Journal, a 2010 finalist for a Pulitzer Prize.","protected":false,"followers_count":1512,"friends_count":607,"listed_count":101,"created_at":"Mon Sep 22 18:32:23 +0000 2008","favourites_count":5,"utc_offset":-28800,"time_zone":"Pacific Time (US & Canada)","geo_enabled":false,"verified":false,"statuses_count":2679,"lang":"en","contributors_enabled":false,"is_translator":false,"profile_background_color":"B2BEDE","profile_background_image_url":"http:\/\/a0.twimg.com\/images\/themes\/theme13\/bg.gif","profile_background_image_url_https":"https:\/\/si0.twimg.com\/images\/themes\/theme13\/bg.gif","profile_background_tile":false,"profile_image_url":"http:\/\/a0.twimg.com\/profile_images\/898323221\/George_twitter_normal.jpg","profile_image_url_https":"https:\/\/si0.twimg.com\/profile_images\/898323221\/George_twitter_normal.jpg","profile_link_color":"4474A6","profile_sidebar_border_color":"EEEEEE","profile_sidebar_fill_color":"FFFFFF","profile_text_color":"333333","profile_use_background_image":true,"default_profile":false,"default_profile_image":false,"following":null,"follow_request_sent":null,"notifications":null},"geo":null,"coordinates":null,"place":null,"contributors":null,"retweet_count":0,"favorite_count":0,"favorited":false,"retweeted":false,"possibly_sensitive":false,"lang":"en"}